scrapyduler/__init__.py
scrapyduler/launcher.py
scrapyduler-1.0.2.dist-info/METADATA
scrapyduler-1.0.2.dist-info/WHEEL
scrapyduler-1.0.2.dist-info/top_level.txt
scrapyduler-1.0.2.dist-info/RECORD
