Metadata-Version: 2.1
Name: scrapyduler
Version: 1.0.2
Summary: Scrapyd launcher module that schedules scrapy spiders by time
Author-email: Dmitriy Chuenkov <slymit@gmail.com>
License: BSD-3-Clause
Project-URL: Homepage, https://github.com/slymit/scrapyduler
Keywords: scrapy,scrapyd,scheduler,launcher
Classifier: License :: OSI Approved :: BSD License
Classifier: Operating System :: OS Independent
Classifier: Programming Language :: Python :: 3
Classifier: Programming Language :: Python :: 3.7
Classifier: Programming Language :: Python :: 3.8
Classifier: Programming Language :: Python :: 3.9
Classifier: Programming Language :: Python :: 3.10
Classifier: Programming Language :: Python :: 3.11
Classifier: Environment :: Console
Classifier: Environment :: No Input/Output (Daemon)
Classifier: Topic :: Internet :: WWW/HTTP
Requires-Python: >=3.7
Requires-Dist: scrapyd >=1.4.2
Requires-Dist: APScheduler ==3.10.1
Requires-Dist: importlib-metadata ; python_version >= "3.7"
